jiaguup/__init__.py
jiaguup/__main__.py
jiaguup/analyze.py
jiaguup/findword.py
jiaguup/mmseg.py
jiaguup/perceptron.py
jiaguup/textrank.py
jiaguup/utils.py
jiaguup/cluster/__init__.py
jiaguup/cluster/base.py
jiaguup/cluster/dbscan.py
jiaguup/cluster/kmeans.py
jiaguup/cluster/text.py
jiaguup/data/stopwords.txt
jiaguup/model/kg.model
jiaguup/model/ner.model
jiaguup/model/pos.model
jiaguup/normal/README.md
jiaguup/segment/README.md
jiaguup/segment/nroute.py
jiaguup/segment/dict/jiagu.dict
jiaguup/segment/dict/user.dict
jiaguup/segment/model/cws.model
jiaguup/sentiment/README.md
jiaguup/sentiment/bayes.py
jiaguup/sentiment/model/sentiment.model
jiaguup/topic/lda.py
jiaguup-0.2.3.dist-info/METADATA
jiaguup-0.2.3.dist-info/WHEEL
jiaguup-0.2.3.dist-info/license
jiaguup-0.2.3.dist-info/top_level.txt
jiaguup-0.2.3.dist-info/RECORD
