Metadata-Version: 2.1
Name: jiaguup
Version: 0.2.3
Summary: jiaguup Natural Language Processing, fix for tensorflow2
Home-page: https://github.com/willsdu/jiaguup
Author: William.Du
Author-email: duyq0519@outlook.com
License: MIT
Platform: UNKNOWN
License-File: license
